{"legislative_session": "2020", "identifier": "SR 33", "title": "Reaffirming sister-state relationship between WV and Taiwan", "from_organization": "~{\"classification\": \"upper\"}", "classification": ["resolution"], "subject": [], "abstracts": [], "other_titles": [], "other_identifiers": [], "actions": [{"description": "Filed for introduction", "date": "2020-02-05", "organization_id": "~{\"classification\": \"upper\"}", "classification": ["filing"], "related_entities": []}, {"description": "Introduced in Senate", "date": "2020-02-05", "organization_id": "~{\"classification\": \"upper\"}", "classification": ["introduction"], "related_entities": []}, {"description": "On Unfinished Business", "date": "2020-02-06", "organization_id": "~{\"classification\": \"upper\"}", "classification": [], "related_entities": []}, {"description": "Immediate consideration", "date": "2020-02-06", "organization_id": "~{\"classification\": \"upper\"}", "classification": [], "related_entities": []}, {"description": "Committee reference dispensed", "date": "2020-02-06", "organization_id": "~{\"classification\": \"upper\"}", "classification": [], "related_entities": []}, {"description": "Adopted (Roll No. 75)", "date": "2020-02-06", "organization_id": "~{\"classification\": \"upper\"}", "classification": [], "related_entities": []}, {"description": "Completed legislative action", "date": "2020-02-06", "organization_id": "~{\"classification\": \"upper\"}", "classification": [], "related_entities": []}], "sponsorships": [{"name": "Blair", "classification": "primary", "entity_type": "person", "primary": true, "person_id": "~{\"name\": \"Blair\"}", "organization_id": null}, {"name": "Baldwin", "classification": "cosponsor", "entity_type": "person", "primary": false, "person_id": "~{\"name\": \"Baldwin\"}", "organization_id": null}, {"name": "Cline", "classification": "cosponsor", "entity_type": "person", "primary": false, "person_id": "~{\"name\": \"Cline\"}", "organization_id": null}, {"name": "Lindsay", "classification": "cosponsor", "entity_type": "person", "primary": false, "person_id": "~{\"name\": \"Lindsay\"}", "organization_id": null}, {"name": "Plymale", "classification": "cosponsor", "entity_type": "person", "primary": false, "person_id": "~{\"name\": \"Plymale\"}", "organization_id": null}, {"name": "Romano", "classification": "cosponsor", "entity_type": "person", "primary": false, "person_id": "~{\"name\": \"Romano\"}", "organization_id": null}, {"name": "Rucker", "classification": "cosponsor", "entity_type": "person", "primary": false, "person_id": "~{\"name\": \"Rucker\"}", "organization_id": null}, {"name": "Stollings", "classification": "cosponsor", "entity_type": "person", "primary": false, "person_id": "~{\"name\": \"Stollings\"}", "organization_id": null}, {"name": "Trump", "classification": "cosponsor", "entity_type": "person", "primary": false, "person_id": "~{\"name\": \"Trump\"}", "organization_id": null}, {"name": "Unger", "classification": "cosponsor", "entity_type": "person", "primary": false, "person_id": "~{\"name\": \"Unger\"}", "organization_id": null}, {"name": "Sypolt", "classification": "cosponsor", "entity_type": "person", "primary": false, "person_id": "~{\"name\": \"Sypolt\"}", "organization_id": null}], "related_bills": [], "versions": [{"note": "Introduced Version", "links": [{"url": "http://www.legis.state.wv.us/Bill_Status/bills_text.cfm?billdoc=SR33%20INTR.htm&yr=2020&sesstype=RS&i=33&houseorig=s&billtype=r", "media_type": "text/html"}], "date": "", "classification": ""}], "documents": [], "sources": [{"url": "http://www.legis.state.wv.us/Bill_Status/Resolution_History.cfm?year=2020&sessiontype=RS&input4=33&billtype=r&houseorig=s&btype=res", "note": ""}], "extras": {}, "_id": "ac1a5764-627e-11eb-b098-0242ac120002"}