{"name": "Wayne Clark", "other_names": [], "identifiers": [], "gender": "", "birth_date": "", "death_date": "", "image": "http://www.legis.state.wv.us/images/members/2021/house/clark_wayne.jpg", "biography": "", "contact_details": [{"type": "email", "value": "wayne.clark@wvhouse.gov", "note": "Capitol Office"}, {"type": "voice", "value": "(304) 340-3366", "note": "Capitol Office"}, {"type": "address", "value": "Room 218E, Building 1\nState Capitol Complex\nCharleston, WV 25305", "note": "Capitol Office"}], "links": [{"note": "", "url": "http://www.legis.state.wv.us/House/lawmaker.cfm?member=Delegate+Clark"}], "sources": [{"url": "http://www.legis.state.wv.us/House/lawmaker.cfm?member=Delegate+Clark", "note": ""}], "extras": {}, "_id": "b89b7460-64e9-11eb-abb0-0242ac120002"}