{"legislative_session": "2020", "identifier": "SB 511", "title": "Regulating pawnbrokers", "from_organization": "~{\"classification\": \"upper\"}", "classification": ["bill"], "subject": ["Professions and Occupations"], "abstracts": [], "other_titles": [], "other_identifiers": [], "actions": [{"description": "Filed for introduction", "date": "2020-01-16", "organization_id": "~{\"classification\": \"upper\"}", "classification": ["filing"], "related_entities": []}, {"description": "To Judiciary", "date": "2020-01-16", "organization_id": "~{\"classification\": \"upper\"}", "classification": ["referral-committee"], "related_entities": []}, {"description": "Introduced in Senate", "date": "2020-01-16", "organization_id": "~{\"classification\": \"upper\"}", "classification": ["introduction"], "related_entities": []}, {"description": "To Judiciary", "date": "2020-01-16", "organization_id": "~{\"classification\": \"upper\"}", "classification": ["referral-committee"], "related_entities": []}, {"description": "Committee substitute reported", "date": "2020-01-29", "organization_id": "~{\"classification\": \"upper\"}", "classification": [], "related_entities": []}, {"description": "On 1st reading", "date": "2020-01-30", "organization_id": "~{\"classification\": \"upper\"}", "classification": [], "related_entities": []}, {"description": "Read 1st time", "date": "2020-01-30", "organization_id": "~{\"classification\": \"upper\"}", "classification": ["reading-1"], "related_entities": []}, {"description": "On 2nd reading", "date": "2020-01-31", "organization_id": "~{\"classification\": \"upper\"}", "classification": [], "related_entities": []}, {"description": "Laid over on 2nd reading 1/31/20", "date": "2020-01-31", "organization_id": "~{\"classification\": \"upper\"}", "classification": [], "related_entities": []}, {"description": "Read 2nd time", "date": "2020-02-03", "organization_id": "~{\"classification\": \"upper\"}", "classification": ["reading-2"], "related_entities": []}, {"description": "Floor amendment adopted (Voice vote)", "date": "2020-02-03", "organization_id": "~{\"classification\": \"upper\"}", "classification": [], "related_entities": []}, {"description": "On 3rd reading", "date": "2020-02-04", "organization_id": "~{\"classification\": \"upper\"}", "classification": [], "related_entities": []}, {"description": "Referred to Rules on 3rd reading", "date": "2020-02-04", "organization_id": "~{\"classification\": \"upper\"}", "classification": ["referral-committee"], "related_entities": []}, {"description": "Reported do pass", "date": "2020-02-24", "organization_id": "~{\"classification\": \"upper\"}", "classification": ["committee-passage"], "related_entities": []}, {"description": "On 3rd reading", "date": "2020-02-25", "organization_id": "~{\"classification\": \"upper\"}", "classification": [], "related_entities": []}, {"description": "Amended on 3rd reading  (Voice vote)", "date": "2020-02-25", "organization_id": "~{\"classification\": \"upper\"}", "classification": [], "related_entities": []}, {"description": "Read 3rd time", "date": "2020-02-25", "organization_id": "~{\"classification\": \"upper\"}", "classification": ["reading-3"], "related_entities": []}, {"description": "Passed Senate with amended title (Roll No. 253)", "date": "2020-02-25", "organization_id": "~{\"classification\": \"upper\"}", "classification": ["passage"], "related_entities": []}, {"description": "Ordered to House", "date": "2020-02-25", "organization_id": "~{\"classification\": \"upper\"}", "classification": [], "related_entities": []}, {"description": "Introduced in House", "date": "2020-02-26", "organization_id": "~{\"classification\": \"lower\"}", "classification": ["introduction"], "related_entities": []}, {"description": "To Judiciary", "date": "2020-02-26", "organization_id": "~{\"classification\": \"lower\"}", "classification": ["referral-committee"], "related_entities": []}, {"description": "To House Judiciary", "date": "2020-02-26", "organization_id": "~{\"classification\": \"lower\"}", "classification": ["referral-committee"], "related_entities": []}], "sponsorships": [{"name": "Jeffries", "classification": "primary", "entity_type": "person", "primary": true, "person_id": "~{\"name\": \"Jeffries\"}", "organization_id": null}, {"name": "Lindsay", "classification": "cosponsor", "entity_type": "person", "primary": false, "person_id": "~{\"name\": \"Lindsay\"}", "organization_id": null}], "related_bills": [], "versions": [{"note": "Second Engrossment Committee Substitute", "links": [{"url": "http://www.legis.state.wv.us/Bill_Status/bills_text.cfm?billdoc=SB511%20SUB1%20ENG2.htm&yr=2020&sesstype=RS&i=511", "media_type": "text/html"}], "date": "", "classification": ""}, {"note": "Engrossed Committee Substitute", "links": [{"url": "http://www.legis.state.wv.us/Bill_Status/bills_text.cfm?billdoc=SB511%20SUB1%20ENG.htm&yr=2020&sesstype=RS&i=511", "media_type": "text/html"}], "date": "", "classification": ""}, {"note": "Committee Substitute", "links": [{"url": "http://www.legis.state.wv.us/Bill_Status/bills_text.cfm?billdoc=SB511%20SUB1.htm&yr=2020&sesstype=RS&i=511", "media_type": "text/html"}], "date": "", "classification": ""}, {"note": "Introduced Version", "links": [{"url": "http://www.legis.state.wv.us/Bill_Status/bills_text.cfm?billdoc=SB511%20INTR.htm&yr=2020&sesstype=RS&i=511", "media_type": "text/html"}], "date": "", "classification": ""}, {"note": "SB511 SFA _1 JEFFRIES 2-24 adopted.htm", "links": [{"url": "http://www.legis.state.wv.us/legisdocs/chamber/2020/RS/floor_amends/SB511 SFA _1 JEFFRIES 2-24 adopted.htm", "media_type": "text/html"}], "date": "", "classification": ""}, {"note": "SB511 SFAT _2 JEFFRIES 2-20 adopted.htm", "links": [{"url": "http://www.legis.state.wv.us/legisdocs/chamber/2020/RS/floor_amends/SB511 SFAT _2 JEFFRIES 2-20 adopted.htm", "media_type": "text/html"}], "date": "", "classification": ""}, {"note": "SB511 SFA _1 LINDSAY 2-3 adopted.htm", "links": [{"url": "http://www.legis.state.wv.us/legisdocs/chamber/2020/RS/floor_amends/SB511 SFA _1 LINDSAY 2-3 adopted.htm", "media_type": "text/html"}], "date": "", "classification": ""}], "documents": [], "sources": [{"url": "http://www.legis.state.wv.us/Bill_Status/Bills_history.cfm?input=511&year=2020&sessiontype=RS&btype=bill", "note": ""}], "extras": {}, "_id": "c528a574-67d5-11eb-8dd7-0242ac120002"}